WDT/__init__.py
WDT/wdt.py
tests/__init__.py
tests/test_WDT.py
WDT-0.3.1.dist-info/METADATA
WDT-0.3.1.dist-info/WHEEL
WDT-0.3.1.dist-info/top_level.txt
WDT-0.3.1.dist-info/RECORD
