Metadata-Version: 2.1
Name: WDT
Version: 0.3.1
Summary: Watch Dog Timer for python.
Home-page: https://github.com/mastnk/WDT
Author: Masayuki Tanaka
Author-email: mastnk@gmail.com
License: UNKNOWN
Platform: UNKNOWN
Classifier: License :: OSI Approved :: MIT License
Classifier: Programming Language :: Python :: 3.6
